collibra_connector/__init__.py
collibra_connector/async_connector.py
collibra_connector/cli.py
collibra_connector/connector.py
collibra_connector/helpers.py
collibra_connector/lineage.py
collibra_connector/models.py
collibra_connector/py.typed
collibra_connector/telemetry.py
collibra_connector/testing.py
collibra_connector/api/Asset.py
collibra_connector/api/Attribute.py
collibra_connector/api/Base.py
collibra_connector/api/Comment.py
collibra_connector/api/Community.py
collibra_connector/api/Domain.py
collibra_connector/api/Exceptions.py
collibra_connector/api/Metadata.py
collibra_connector/api/OutputModule.py
collibra_connector/api/Relation.py
collibra_connector/api/Responsibility.py
collibra_connector/api/Search.py
collibra_connector/api/User.py
collibra_connector/api/Utils.py
collibra_connector/api/Workflow.py
collibra_connector/api/__init__.py
collibra_connector-1.1.1.dist-info/licenses/LICENSE
collibra_connector-1.1.1.dist-info/METADATA
collibra_connector-1.1.1.dist-info/WHEEL
collibra_connector-1.1.1.dist-info/entry_points.txt
collibra_connector-1.1.1.dist-info/top_level.txt
collibra_connector-1.1.1.dist-info/RECORD
