Metadata-Version: 2.4
Name: collibra-connector
Version: 1.1.1
Summary: An UNOFFICIAL standard Python connector for the Collibra Data Governance Center API with full type safety, async support, and enterprise features.
Author-email: Raul Dalgamonni <rauldalgamonnialonso@gmail.com>
Project-URL: Homepage, https://github.com/rauldaal/collibra-python-connector
Project-URL: Bug Tracker, https://github.com/rauldaal/collibra-python-connector/issues
Project-URL: Documentation, https://github.com/rauldaal/collibra-python-connector#readme
Project-URL: Changelog, https://github.com/rauldaal/collibra-python-connector/blob/main/CHANGELOG.md
Keywords: collibra,data-governance,data-catalog,api-client,data-lineage,metadata-management
Classifier: Programming Language :: Python :: 3
Classifier: Programming Language :: Python :: 3.8
Classifier: Programming Language :: Python :: 3.9
Classifier: Programming Language :: Python :: 3.10
Classifier: Programming Language :: Python :: 3.11
Classifier: Programming Language :: Python :: 3.12
Classifier: Programming Language :: Python :: 3.13
Classifier: License :: OSI Approved :: MIT License
Classifier: Operating System :: OS Independent
Classifier: Topic :: Software Development :: Libraries :: Python Modules
Classifier: Intended Audience :: Developers
Classifier: Typing :: Typed
Classifier: Framework :: Pydantic :: 2
Classifier: Development Status :: 5 - Production/Stable
Requires-Python: >=3.8
License-File: LICENSE
Requires-Dist: requests>=2.20.0
Requires-Dist: pydantic>=2.0.0
Provides-Extra: async
Requires-Dist: httpx>=0.25.0; extra == "async"
Provides-Extra: cli
Requires-Dist: click>=8.0.0; extra == "cli"
Requires-Dist: pandas>=1.3.0; extra == "cli"
Provides-Extra: telemetry
Requires-Dist: opentelemetry-api>=1.20.0; extra == "telemetry"
Requires-Dist: opentelemetry-sdk>=1.20.0; extra == "telemetry"
Requires-Dist: opentelemetry-exporter-otlp>=1.20.0; extra == "telemetry"
Provides-Extra: pandas
Requires-Dist: pandas>=1.3.0; extra == "pandas"
Provides-Extra: all
Requires-Dist: httpx>=0.25.0; extra == "all"
Requires-Dist: click>=8.0.0; extra == "all"
Requires-Dist: pandas>=1.3.0; extra == "all"
Requires-Dist: opentelemetry-api>=1.20.0; extra == "all"
Requires-Dist: opentelemetry-sdk>=1.20.0; extra == "all"
Requires-Dist: opentelemetry-exporter-otlp>=1.20.0; extra == "all"
Provides-Extra: dev
Requires-Dist: pytest>=7.0.0; extra == "dev"
Requires-Dist: pytest-cov>=4.0.0; extra == "dev"
Requires-Dist: pytest-asyncio>=0.21.0; extra == "dev"
Requires-Dist: mypy>=1.0.0; extra == "dev"
Requires-Dist: types-requests>=2.28.0; extra == "dev"
Requires-Dist: ruff>=0.1.0; extra == "dev"
Requires-Dist: httpx>=0.25.0; extra == "dev"
Requires-Dist: click>=8.0.0; extra == "dev"
Requires-Dist: pandas>=1.3.0; extra == "dev"
Dynamic: license-file
